LICENSE
MANIFEST.in
README.md
setup.py
django_oauth_tokens.egg-info/PKG-INFO
django_oauth_tokens.egg-info/SOURCES.txt
django_oauth_tokens.egg-info/dependency_links.txt
django_oauth_tokens.egg-info/not-zip-safe
django_oauth_tokens.egg-info/requires.txt
django_oauth_tokens.egg-info/top_level.txt
oauth_tokens/__init__.py
oauth_tokens/__init__.pyc
oauth_tokens/admin.py
oauth_tokens/admin.pyc
oauth_tokens/api.py
oauth_tokens/api.pyc
oauth_tokens/base.py
oauth_tokens/base.pyc
oauth_tokens/exceptions.py
oauth_tokens/exceptions.pyc
oauth_tokens/factories.py
oauth_tokens/factories.pyc
oauth_tokens/lock.py
oauth_tokens/lock.pyc
oauth_tokens/models.py
oauth_tokens/models.pyc
oauth_tokens/tests.py
oauth_tokens/tests.pyc
oauth_tokens/migrations/0001_initial.py
oauth_tokens/migrations/0001_initial.pyc
oauth_tokens/migrations/0002_auto__chg_field_accesstoken_expires.py
oauth_tokens/migrations/0002_auto__chg_field_accesstoken_expires.pyc
oauth_tokens/migrations/0003_auto__add_usercredentials__add_field_accesstoken_user.py
oauth_tokens/migrations/0003_auto__add_usercredentials__add_field_accesstoken_user.pyc
oauth_tokens/migrations/0004_auto__add_field_usercredentials_name.py
oauth_tokens/migrations/0004_auto__add_field_usercredentials_name.pyc
oauth_tokens/migrations/0005_auto__add_field_usercredentials_active__chg_field_usercredentials_prov.py
oauth_tokens/migrations/0005_auto__add_field_usercredentials_active__chg_field_usercredentials_prov.pyc
oauth_tokens/migrations/0006_auto__chg_field_accesstoken_access_token.py
oauth_tokens/migrations/0006_auto__chg_field_accesstoken_access_token.pyc
oauth_tokens/migrations/0007_auto.py
oauth_tokens/migrations/0007_auto.pyc
oauth_tokens/migrations/0008_auto.py
oauth_tokens/migrations/0008_auto.pyc
oauth_tokens/migrations/0009_auto__del_field_accesstoken_user__del_field_accesstoken_granted__del_f.py
oauth_tokens/migrations/0009_auto__del_field_accesstoken_user__del_field_accesstoken_granted__del_f.pyc
oauth_tokens/migrations/__init__.py
oauth_tokens/migrations/__init__.pyc
oauth_tokens/providers/__init__.py
oauth_tokens/providers/__init__.pyc
oauth_tokens/providers/facebook.py
oauth_tokens/providers/facebook.pyc
oauth_tokens/providers/odnoklassniki.py
oauth_tokens/providers/odnoklassniki.pyc
