Metadata-Version: 1.1
Name: django-oauth-tokens
Version: 0.6.2
Summary: Application for getting, refreshing and storing OAuth access_tokens for Django standalone applications
Home-page: https://github.com/ramusus/django-oauth-tokens
Author: ramusus
Author-email: ramusus@gmail.com
License: BSD
Download-URL: http://pypi.python.org/pypi/django-oauth-tokens
Platform: UNKNOWN
Classifier: Development Status :: 4 - Beta
Classifier: Environment :: Web Environment
Classifier: Intended Audience :: Developers
Classifier: License :: OSI Approved :: BSD License
Classifier: Operating System :: OS Independent
Classifier: Programming Language :: Python
Classifier: Topic :: Software Development :: Libraries :: Python Modules
